setup.py
gauthify/__init__.py
gauthify/common.py
gauthify.egg-info/PKG-INFO
gauthify.egg-info/SOURCES.txt
gauthify.egg-info/dependency_links.txt
gauthify.egg-info/not-zip-safe
gauthify.egg-info/requires.txt
gauthify.egg-info/top_level.txt