Metadata-Version: 1.0
Name: gauthify
Version: 2.00
Summary: API library for GAuthify.com (Google Authenticator, SMS, email multi factor authentication).
Home-page: https://www.gauthify.com
Author: GAuthify
Author-email: support@gauthify.com
License: MIT
Platform: UNKNOWN
